copulagp/__init__.py
copulagp/MI/__init__.py
copulagp/MI/ksg.py
copulagp/MI/marginal.py
copulagp/MI/mi.py
copulagp/MI/mine.py
copulagp/bvcopula/__init__.py
copulagp/bvcopula/conf.py
copulagp/bvcopula/distributions.py
copulagp/bvcopula/infer.py
copulagp/bvcopula/likelihoods.py
copulagp/bvcopula/models.py
copulagp/marginal/MI.py
copulagp/marginal/__init__.py
copulagp/marginal/nonparametric.py
copulagp/marginal/order.py
copulagp/select_copula/__init__.py
copulagp/select_copula/conf.py
copulagp/select_copula/heuristics.py
copulagp/select_copula/importance.py
copulagp/select_copula/light.py
copulagp/select_copula/simple_greedy.py
copulagp/select_copula/smart_greedy.py
copulagp/synthetic_data/__init__.py
copulagp/synthetic_data/synthetic_data.py
copulagp/train/__init__.py
copulagp/train/checkpoints.py
copulagp/train/train_next_tree.py
copulagp/train/train_vine.py
copulagp/utils/__init__.py
copulagp/utils/data_loader.py
copulagp/utils/model_loader.py
copulagp/utils/plot_conf.py
copulagp/utils/plot_helpers.py
copulagp/utils/student.py
copulagp/utils/util.py
copulagp/vine/__init__.py
copulagp/vine/vine.py
copulagp/vine/vine_loader.py
copulagp-0.0.5.dist-info/LICENSE
copulagp-0.0.5.dist-info/METADATA
copulagp-0.0.5.dist-info/WHEEL
copulagp-0.0.5.dist-info/top_level.txt
copulagp-0.0.5.dist-info/RECORD
