Metadata-Version: 2.1
Name: copulagp
Version: 0.0.5
Summary: A Copula-GP (Gaussian Process) package
Home-page: https://github.com/NinelK/CopulaGP
Author: Nina Kudryashova
Author-email: nkudryas@ed.ac.uk
License: UNKNOWN
Project-URL: Bug Tracker, https://github.com/NinelK/CopulaGP/issues
Platform: UNKNOWN
Classifier: Programming Language :: Python :: 3
Classifier: License :: OSI Approved :: GNU General Public License v3 (GPLv3)
Classifier: Operating System :: OS Independent
Requires-Python: >=3.6
License-File: LICENSE
Requires-Dist: fastkde (>=1.0.14)
Requires-Dist: gpytorch (>=1.2.0)
Requires-Dist: matplotlib (>=3.3.1)
Requires-Dist: numpy (>=1.19.1)
Requires-Dist: pytest (>=5.3.2)
Requires-Dist: scipy (>=1.5.2)
Requires-Dist: torch (>=1.6)
